pyblockpaysio/__init__.py
pyblockpaysio/functions.py
pyblockpaysio-1.0.1.dist-info/METADATA
pyblockpaysio-1.0.1.dist-info/WHEEL
pyblockpaysio-1.0.1.dist-info/top_level.txt
pyblockpaysio-1.0.1.dist-info/RECORD
