Metadata-Version: 2.1
Name: pyblockpaysio
Version: 1.0.1
Summary: This library let integrate your application to our platform then use all service of cripto currencies that us have for you
Home-page: https://gt.globalcoin.co/ctorres/pyblockpays
Author: Carlos Torres - Labsatoshi
Author-email: carlos.torres@labsatoshi.com
License: MIT
Download-URL: https://gt.globalcoin.co/ctorres/pyblockpays/-/tree/1.0.0
Keywords: blockpays,payments,criptos
Platform: UNKNOWN
Requires-Dist: requests
